deepqlearn/__init__.py
deepqlearn/agent.py
deepqlearn/network.py
deepqlearn/replay_buffer.py
deepqlearn/train.py
deepqlearn-0.1.1.dist-info/METADATA
deepqlearn-0.1.1.dist-info/WHEEL
deepqlearn-0.1.1.dist-info/licenses/LICENSE
deepqlearn-0.1.1.dist-info/RECORD
