Metadata-Version: 2.4
Name: deepqlearn
Version: 0.1.1
Summary: A simple Deep Q-Network implementation in PyTorch
Project-URL: Homepage, https://github.com/yourusername/deepqlearn
Project-URL: Issues, https://github.com/yourusername/deepqlearn/issues
Author: Prathamesh Jadhav
License: MIT
License-File: LICENSE
Keywords: deep q network,dqn,reinforcement learning
Classifier: License :: OSI Approved :: MIT License
Classifier: Programming Language :: Python :: 3
Requires-Python: >=3.8
